nima_io/__init__.py
nima_io/__main__.py
nima_io/py.typed
nima_io/read.py
nima_io-0.3.12.dist-info/METADATA
nima_io-0.3.12.dist-info/WHEEL
nima_io-0.3.12.dist-info/entry_points.txt
nima_io-0.3.12.dist-info/licenses/LICENSE.txt
nima_io-0.3.12.dist-info/RECORD
