Metadata-Version: 2.3
Name: nima_io
Version: 0.3.12
Summary: A project to read microscopy files.
Project-URL: Bug Tracker, https://github.com/darosio/nima_io/issues
Project-URL: Changelog, https://github.com/darosio/nima_io/blob/main/CHANGELOG.md
Project-URL: Documentation, https://nima-io.readthedocs.io
Project-URL: Github releases, https://github.com/darosio/nima_io/releases
Project-URL: Homepage, https://github.com/darosio/nima_io
Author-email: Daniele Arosio <darosio@duck.com>
License-Expression: BSD-3-Clause
License-File: LICENSE.txt
Keywords: Bioimage,Image Analysis,Metadata,Open Microscopy,Tiled Images
Classifier: Development Status :: 3 - Alpha
Classifier: Environment :: Console
Classifier: Intended Audience :: Science/Research
Classifier: Operating System :: OS Independent
Classifier: Programming Language :: Python :: 3 :: Only
Classifier: Programming Language :: Python :: 3.10
Classifier: Programming Language :: Python :: 3.11
Classifier: Programming Language :: Python :: 3.12
Classifier: Programming Language :: Unix Shell
Classifier: Topic :: Scientific/Engineering
Requires-Python: <3.13,>=3.10
Requires-Dist: bioio-bioformats<=1.0.0
Requires-Dist: click<=8.1.7
Requires-Dist: dask-image<=2024.5.3
Requires-Dist: jpype1<=1.5.0
Requires-Dist: lxml<=5.3.0
Requires-Dist: numpy<=2.1.0
Requires-Dist: pims<=0.7
Requires-Dist: pyometiff<=1.0.0
Requires-Dist: readlif<=0.6.5
Requires-Dist: scyjava<=1.10.0
Requires-Dist: setuptools
Provides-Extra: dev
Requires-Dist: bfio<=2.4.2; extra == 'dev'
Requires-Dist: commitizen<=3.29.0; extra == 'dev'
Requires-Dist: ipykernel; extra == 'dev'
Requires-Dist: jupyter; extra == 'dev'
Requires-Dist: matplotlib<=3.9.2; extra == 'dev'
Requires-Dist: pre-commit<=3.8.0; extra == 'dev'
Requires-Dist: pylsp-mypy; extra == 'dev'
Requires-Dist: ruff-lsp; extra == 'dev'
Requires-Dist: ruff<=0.6.1; extra == 'dev'
Requires-Dist: scikit-image<=0.24.0; extra == 'dev'
Provides-Extra: docs
Requires-Dist: autodocsumm<=0.2.13; extra == 'docs'
Requires-Dist: nbsphinx<=0.9.5; extra == 'docs'
Requires-Dist: pydata-sphinx-theme<=0.15.4; extra == 'docs'
Requires-Dist: sphinx-autodoc-typehints<=2.2.3; extra == 'docs'
Requires-Dist: sphinx-click<=6.0.0; extra == 'docs'
Requires-Dist: sphinx<=8.0.2; extra == 'docs'
Requires-Dist: sphinxcontrib-plantuml<=0.30; extra == 'docs'
Requires-Dist: xmltodict; extra == 'docs'
Provides-Extra: tests
Requires-Dist: coverage[toml]<=7.6.1; extra == 'tests'
Requires-Dist: mypy<=1.11.1; extra == 'tests'
Requires-Dist: pygments<=2.18.0; extra == 'tests'
Requires-Dist: pytest<=8.3.2; extra == 'tests'
Requires-Dist: types-click<=7.1.8; extra == 'tests'
Requires-Dist: xdoctest<=1.2.0; extra == 'tests'
